{
  "generatedAt": "2026-07-04T10:13:28.319Z",
  "fileUrl": "file:///E:/Websites/Bharat-Metals/bharat-metals-website/index.html",
  "viewports": [
    {
      "name": "desktop-1440",
      "width": 1440,
      "height": 1200,
      "screenshot": "qa/mega-cdp-desktop-1440.png",
      "metrics": {
        "viewport": {
          "width": 1440,
          "height": 1200
        },
        "document": {
          "clientWidth": 1440,
          "scrollWidth": 1440,
          "bodyScrollWidth": 1440,
          "hasHorizontalOverflow": false
        },
        "header": {
          "logo": {
            "x": 110,
            "y": 40,
            "width": 236,
            "height": 78.65625,
            "top": 40,
            "right": 346,
            "bottom": 118.65625,
            "left": 110
          },
          "navToggle": {
            "x": 0,
            "y": 0,
            "width": 0,
            "height": 0,
            "top": 0,
            "right": 0,
            "bottom": 0,
            "left": 0
          },
          "navToggleDisplay": "none",
          "navAriaExpanded": "false"
        },
        "hero": {
          "h1": {
            "x": 110,
            "y": 220.9375,
            "width": 530.09375,
            "height": 207.3125,
            "top": 220.9375,
            "right": 640.09375,
            "bottom": 428.25,
            "left": 110
          },
          "media": {
            "x": 682.09375,
            "y": 177.65625,
            "width": 647.90625,
            "height": 616.21875,
            "top": 177.65625,
            "right": 1330,
            "bottom": 793.875,
            "left": 682.09375
          }
        },
        "topBar": {
          "line": {
            "x": 110,
            "y": 10.328125,
            "width": 380.1875,
            "height": 19.34375,
            "top": 10.328125,
            "right": 490.1875,
            "bottom": 29.671875,
            "left": 110
          },
          "icons": {
            "x": 1155,
            "y": 8.5,
            "width": 175,
            "height": 23,
            "top": 8.5,
            "right": 1330,
            "bottom": 31.5,
            "left": 1155
          }
        },
        "mobileNav": {
          "beforeOpenClass": "site-nav",
          "dropdownAriaExpanded": "false"
        },
        "portfolioMenu": {
          "exists": true,
          "flyoutCount": 4,
          "productButtonExpanded": "true",
          "menuOpacity": "1",
          "flyoutOpacity": "1",
          "flyoutNoGap": true,
          "rodsSeparate": true,
          "barsSeparate": true
        }
      },
      "mobileNavCheck": null
    },
    {
      "name": "tablet-768",
      "width": 768,
      "height": 1100,
      "screenshot": "qa/mega-cdp-tablet-768.png",
      "metrics": {
        "viewport": {
          "width": 768,
          "height": 1100
        },
        "document": {
          "clientWidth": 768,
          "scrollWidth": 768,
          "bodyScrollWidth": 768,
          "hasHorizontalOverflow": false
        },
        "header": {
          "logo": {
            "x": 16,
            "y": 43.671875,
            "width": 206,
            "height": 68.65625,
            "top": 43.671875,
            "right": 222,
            "bottom": 112.328125,
            "left": 16
          },
          "navToggle": {
            "x": 708,
            "y": 56,
            "width": 44,
            "height": 44,
            "top": 56,
            "right": 752,
            "bottom": 100,
            "left": 708
          },
          "navToggleDisplay": "flex",
          "navAriaExpanded": "false"
        },
        "hero": {
          "h1": {
            "x": 16,
            "y": 218.28125,
            "width": 660,
            "height": 84.65625,
            "top": 218.28125,
            "right": 676,
            "bottom": 302.9375,
            "left": 16
          },
          "media": {
            "x": 16,
            "y": 639.453125,
            "width": 736,
            "height": 460,
            "top": 639.453125,
            "right": 752,
            "bottom": 1099.453125,
            "left": 16
          }
        },
        "topBar": {
          "line": {
            "x": 16,
            "y": 10.328125,
            "width": 543,
            "height": 19.34375,
            "top": 10.328125,
            "right": 559,
            "bottom": 29.671875,
            "left": 16
          },
          "icons": {
            "x": 577,
            "y": 8.5,
            "width": 175,
            "height": 23,
            "top": 8.5,
            "right": 752,
            "bottom": 31.5,
            "left": 577
          }
        },
        "mobileNav": {
          "beforeOpenClass": "site-nav",
          "dropdownAriaExpanded": "false"
        },
        "portfolioMenu": {
          "exists": true,
          "flyoutCount": 4,
          "productButtonExpanded": "false",
          "menuOpacity": "1",
          "flyoutOpacity": "1",
          "flyoutNoGap": true,
          "rodsSeparate": true,
          "barsSeparate": true
        }
      },
      "mobileNavCheck": null
    },
    {
      "name": "mobile-390",
      "width": 390,
      "height": 1000,
      "screenshot": "qa/mega-cdp-mobile-390.png",
      "metrics": {
        "viewport": {
          "width": 390,
          "height": 1000
        },
        "document": {
          "clientWidth": 390,
          "scrollWidth": 390,
          "bodyScrollWidth": 390,
          "hasHorizontalOverflow": false
        },
        "header": {
          "logo": {
            "x": 0,
            "y": 69,
            "width": 162,
            "height": 54,
            "top": 69,
            "right": 162,
            "bottom": 123,
            "left": 0
          },
          "navToggle": {
            "x": 346,
            "y": 74,
            "width": 44,
            "height": 44,
            "top": 74,
            "right": 390,
            "bottom": 118,
            "left": 346
          },
          "navToggleDisplay": "flex",
          "navAriaExpanded": "false"
        },
        "hero": {
          "h1": {
            "x": 12,
            "y": 215.796875,
            "width": 366,
            "height": 87.09375,
            "top": 215.796875,
            "right": 378,
            "bottom": 302.890625,
            "left": 12
          },
          "media": {
            "x": 12,
            "y": 861.515625,
            "width": 366,
            "height": 228.75,
            "top": 861.515625,
            "right": 378,
            "bottom": 1090.265625,
            "left": 12
          }
        },
        "topBar": {
          "line": {
            "x": 12,
            "y": 8,
            "width": 366,
            "height": 14,
            "top": 8,
            "right": 378,
            "bottom": 22,
            "left": 12
          },
          "icons": {
            "x": 12,
            "y": 30,
            "width": 366,
            "height": 23,
            "top": 30,
            "right": 378,
            "bottom": 53,
            "left": 12
          }
        },
        "mobileNav": {
          "beforeOpenClass": "site-nav",
          "dropdownAriaExpanded": "false"
        },
        "portfolioMenu": {
          "exists": true,
          "flyoutCount": 4,
          "productButtonExpanded": "false",
          "menuOpacity": "1",
          "flyoutOpacity": "1",
          "flyoutNoGap": true,
          "rodsSeparate": true,
          "barsSeparate": true
        }
      },
      "mobileNavCheck": {
        "afterToggle": {
          "navOpen": true,
          "ariaExpanded": "true"
        },
        "afterDropdown": {
          "ariaExpanded": "true",
          "groupOpen": true
        },
        "afterPortfolio": {
          "ariaExpanded": "true",
          "menuOpen": true,
          "flyoutExpanded": "true",
          "flyoutOpen": true
        },
        "afterEscape": {
          "navOpen": false,
          "ariaExpanded": "false"
        }
      }
    }
  ]
}
